zoom_python_client/__init__.py
zoom_python_client/api_client.py
zoom_python_client/client_components/__init__.py
zoom_python_client/client_components/calendars/__init__.py
zoom_python_client/client_components/calendars/calendars_component.py
zoom_python_client/client_components/meeting_livestreams/__init__.py
zoom_python_client/client_components/meeting_livestreams/meeting_livestreams_component.py
zoom_python_client/client_components/meetings/__init__.py
zoom_python_client/client_components/meetings/meetings_component.py
zoom_python_client/client_components/rooms/__init__.py
zoom_python_client/client_components/rooms/rooms_component.py
zoom_python_client/client_components/users/__init__.py
zoom_python_client/client_components/users/users_component.py
zoom_python_client/client_components/webinar_livestreams/__init__.py
zoom_python_client/client_components/webinar_livestreams/webinar_livestreams_component.py
zoom_python_client/client_components/webinars/__init__.py
zoom_python_client/client_components/webinars/webinars_component.py
zoom_python_client/utils/__init__.py
zoom_python_client/utils/file_system.py
zoom_python_client/utils/logger.py
zoom_python_client/utils/typed_dict_parameters.py
zoom_python_client/zoom_api_client.py
zoom_python_client/zoom_auth_api/__init__.py
zoom_python_client/zoom_auth_api/zoom_auth_api_client.py
zoom_python_client/zoom_client_interface.py
zoom_python_client-0.2.2.dist-info/LICENSE
zoom_python_client-0.2.2.dist-info/METADATA
zoom_python_client-0.2.2.dist-info/WHEEL
zoom_python_client-0.2.2.dist-info/RECORD
