Metadata-Version: 2.1
Name: zoom-python-client
Version: 0.2.2
Summary: Zoom API client for Python using server to server tokens
Home-page: https://github.com/cern-vc/zoom-python-client
License: MIT
Keywords: zoom,api
Author: Rene Fernandez Sanchez
Author-email: rene.fernandez@cern.ch
Maintainer: Rene Fernandez Sanchez
Maintainer-email: rene.fernandez@cern.ch
Requires-Python: >=3.9,<4.0
Classifier: License :: OSI Approved :: MIT License
Classifier: Operating System :: OS Independent
Classifier: Programming Language :: Python :: 3
Classifier: Programming Language :: Python :: 3.9
Classifier: Programming Language :: Python :: 3.10
Classifier: Programming Language :: Python :: 3.11
Requires-Dist: python-dotenv (>=1.0.0,<2.0.0)
Requires-Dist: requests (>=2.31.0,<3.0.0)
Requires-Dist: typing-extensions (>=4.7.1,<5.0.0)
Project-URL: Bug Tracker, https://github.com/cern-vc/zoom-python-client/issues
Project-URL: Repository, https://github.com/cern-vc/zoom-python-client
